llama_index/readers/stripe_docs/__init__.py
llama_index/readers/stripe_docs/base.py
llama_index_readers_stripe_docs-0.4.1.dist-info/METADATA
llama_index_readers_stripe_docs-0.4.1.dist-info/WHEEL
llama_index_readers_stripe_docs-0.4.1.dist-info/licenses/LICENSE
llama_index_readers_stripe_docs-0.4.1.dist-info/RECORD
