Metadata-Version: 2.4
Name: llama-index-readers-stripe-docs
Version: 0.4.1
Summary: llama-index readers stripe_docs integration
Author-email: Your Name <you@example.com>
Maintainer: amorriscode
License-Expression: GPL-3.0-or-later
License-File: LICENSE
Keywords: documentation,stripe
Requires-Python: <4.0,>=3.9
Requires-Dist: defusedxml<0.8,>=0.7.1
Requires-Dist: html2text<2025,>=2024.2.26
Requires-Dist: llama-index-core<0.15,>=0.13.0
Requires-Dist: llama-index-readers-web<0.6,>=0.5.0
Requires-Dist: urllib3<3,>=2.1.0
